bzmicrostitcher/ProcessData.py
bzmicrostitcher/__init__.py
bzmicrostitcher/__main__.py
bzmicrostitcher-0.1.6.dist-info/LICENSE
bzmicrostitcher-0.1.6.dist-info/METADATA
bzmicrostitcher-0.1.6.dist-info/WHEEL
bzmicrostitcher-0.1.6.dist-info/top_level.txt
bzmicrostitcher-0.1.6.dist-info/RECORD
