Metadata-Version: 2.1
Name: bzmicrostitcher
Version: 0.1.6
Summary: A package to stitch microscope images.
Home-page: https://github.com/LungWizard/BZMicroStitcher
Author: Cory Poole
Author-email: cory_poole@urmc.rochester.edu
License: UNKNOWN
Project-URL: Bug Tracker, https://github.com/LungWizard/BZMicroStitcher/issues
Platform: UNKNOWN
Classifier: Programming Language :: Python :: 3
Classifier: License :: OSI Approved :: GNU General Public License v3 or later (GPLv3+)
Classifier: Operating System :: OS Independent
Requires-Python: >=3.6
License-File: LICENSE
Requires-Dist: numpy (>=1.22.1)
Requires-Dist: scipy (>=1.7.3)
Requires-Dist: tifffile (>=2021.11.2)
Requires-Dist: pyside2 (==5.15.1)
Requires-Dist: shiboken2 (==5.15.1)
Requires-Dist: pyglet (==1.4.10)
Requires-Dist: stitch2d (>=1.0)
Requires-Dist: tk (==0.1.0)
Requires-Dist: opencv-contrib-python (==4.5.5.62)
Requires-Dist: ome-types (==0.2.4)
Requires-Dist: datetime (==4.3)
Requires-Dist: openpyxl (==3.0.9)
Requires-Dist: pillow (==9.0.0)
Requires-Dist: scikit-image (>=0.19.1)
